prs/__init__.py
prs/cli.py
prs-0.0.7.dist-info/METADATA
prs-0.0.7.dist-info/RECORD
prs-0.0.7.dist-info/WHEEL
prs-0.0.7.dist-info/entry_points.txt
prs-0.0.7.dist-info/top_level.txt
