Metadata-Version: 2.1
Name: prs
Version: 0.0.7
Summary: prs is a utility that allows you to use Python list comprehensions in shell commands.
Home-page: https://gitlab.com/stavros/prs
Author: Stavros Korokithakis
Author-email: hi@stavros.io
License: MIT
Keywords: prs shell stdin
Platform: UNKNOWN
Classifier: Development Status :: 3 - Alpha
Classifier: Intended Audience :: End Users/Desktop
Classifier: License :: OSI Approved :: MIT License
Classifier: Natural Language :: English
Classifier: Programming Language :: Python :: 3
Classifier: Programming Language :: Python :: 3.4
Classifier: Programming Language :: Python :: 3.5
Classifier: Programming Language :: Python :: 3.6
Requires-Python: >3.0.0
